Topsis_NKushal_101903494/__init__.py
Topsis_NKushal_101903494-0.3.1.dist-info/LICENCE.txt
Topsis_NKushal_101903494-0.3.1.dist-info/METADATA
Topsis_NKushal_101903494-0.3.1.dist-info/WHEEL
Topsis_NKushal_101903494-0.3.1.dist-info/top_level.txt
Topsis_NKushal_101903494-0.3.1.dist-info/RECORD
