Metadata-Version: 2.1
Name: Topsis-NKushal-101903494
Version: 0.3.1
Summary: A TOPSIS calculator
Home-page: UNKNOWN
Author: N Kushal
Author-email: kushal.nov2000@gmail.com
License: MIT
Keywords: TOPSIS
Platform: UNKNOWN
Classifier: Programming Language :: Python :: 3
Classifier: License :: OSI Approved :: MIT License
Classifier: Operating System :: OS Independent
License-File: LICENCE.txt
